datapipeline/__init__.py
datapipeline/plugins.py
datapipeline/runtime.py
datapipeline/analysis/__init__.py
datapipeline/analysis/vector_analyzer.py
datapipeline/analysis/vector/collector.py
datapipeline/analysis/vector/matrix.py
datapipeline/analysis/vector/report.py
datapipeline/build/__init__.py
datapipeline/build/state.py
datapipeline/build/tasks/__init__.py
datapipeline/build/tasks/config.py
datapipeline/build/tasks/metadata.py
datapipeline/build/tasks/scaler.py
datapipeline/build/tasks/schema.py
datapipeline/build/tasks/utils.py
datapipeline/cli/app.py
datapipeline/cli/commands/build.py
datapipeline/cli/commands/contract.py
datapipeline/cli/commands/domain.py
datapipeline/cli/commands/filter.py
datapipeline/cli/commands/inspect.py
datapipeline/cli/commands/list_.py
datapipeline/cli/commands/plugin.py
datapipeline/cli/commands/run.py
datapipeline/cli/commands/run_config.py
datapipeline/cli/commands/serve_pipeline.py
datapipeline/cli/commands/source.py
datapipeline/cli/visuals/__init__.py
datapipeline/cli/visuals/common.py
datapipeline/cli/visuals/labels.py
datapipeline/cli/visuals/runner.py
datapipeline/cli/visuals/sections.py
datapipeline/cli/visuals/sources.py
datapipeline/cli/visuals/sources_basic.py
datapipeline/cli/visuals/sources_off.py
datapipeline/cli/visuals/sources_rich.py
datapipeline/config/__init__.py
datapipeline/config/catalog.py
datapipeline/config/context.py
datapipeline/config/metadata.py
datapipeline/config/postprocess.py
datapipeline/config/project.py
datapipeline/config/resolution.py
datapipeline/config/split.py
datapipeline/config/tasks.py
datapipeline/config/workspace.py
datapipeline/config/dataset/dataset.py
datapipeline/config/dataset/feature.py
datapipeline/config/dataset/loader.py
datapipeline/config/dataset/normalize.py
datapipeline/domain/__init__.py
datapipeline/domain/feature.py
datapipeline/domain/record.py
datapipeline/domain/sample.py
datapipeline/domain/vector.py
datapipeline/filters/filters.py
jerry_thomas-1.0.2.dist-info/licenses/LICENSE
jerry_thomas-1.0.2.dist-info/METADATA
jerry_thomas-1.0.2.dist-info/WHEEL
jerry_thomas-1.0.2.dist-info/entry_points.txt
jerry_thomas-1.0.2.dist-info/top_level.txt
jerry_thomas-1.0.2.dist-info/RECORD
