Metadata-Version: 2.4
Name: jerry-thomas
Version: 1.0.2
Summary: Jerry-Thomas: a stream-first, plugin-friendly data pipeline (mixology-themed CLI)
Author: Anders Skott Lind
License: MIT
Requires-Python: >=3.10
License-File: LICENSE
Requires-Dist: numpy<3.0,>=1.24
Requires-Dist: pydantic>=2.0
Requires-Dist: PyYAML>=5.4
Requires-Dist: tqdm>=4.0
Requires-Dist: jinja2>=3.0
Requires-Dist: rich>=13
Provides-Extra: ml
Requires-Dist: pandas>=2.0; extra == "ml"
Requires-Dist: torch>=2.0; extra == "ml"
Dynamic: license-file
